tornado_image_streamer/__init__.py
tornado_image_streamer/camera_utils.py
tornado_image_streamer/image_stream_handler.py
tornado_image_streamer/run.py
tornado_image_streamer/tornado_utils.py
tornado_image_streamer/static/jquery-3.1.1.min.js
tornado_image_streamer/static/ws_streamer.js
tornado_image_streamer/templates/index.html
tornado_image_streamer-0.5.dist-info/LICENSE
tornado_image_streamer-0.5.dist-info/METADATA
tornado_image_streamer-0.5.dist-info/WHEEL
tornado_image_streamer-0.5.dist-info/entry_points.txt
tornado_image_streamer-0.5.dist-info/top_level.txt
tornado_image_streamer-0.5.dist-info/zip-safe
tornado_image_streamer-0.5.dist-info/RECORD
