Metadata-Version: 2.1
Name: tornado-image-streamer
Version: 0.5
Summary: Tornado web server image streamer
Home-page: https://gitlab.com/hsmit/tornado-image-streamer
Author: Hans Smit
Author-email: jcsmit@xs4all.nl
License: MIT License
Project-URL: Source, https://gitlab.com/hsmit/tornado-image-streamer
Project-URL: Tracker, https://gitlab.com/hsmit/tornado-image-streamer/issues
Keywords: tornado web stream image websocket webcam
Platform: unix
Platform: linux
Platform: osx
Platform: win32
Classifier: Development Status :: 4 - Beta
Classifier: Intended Audience :: Developers
Classifier: Topic :: Software Development :: Build Tools
Classifier: License :: OSI Approved :: MIT License
Classifier: Programming Language :: Python :: 3
Classifier: Programming Language :: Python :: 3.5
Classifier: Programming Language :: Python :: 3.6
Classifier: Programming Language :: Python :: 3.7
Requires-Python: >= 3.5
Requires-Dist: click
Requires-Dist: tornado
Requires-Dist: pillow
Requires-Dist: opencv-python
Requires-Dist: numpy
